phantom_core/__init__.py
phantom_core/cache.py
phantom_core/constants.py
phantom_core/database/__init__.py
phantom_core/database/config.py
phantom_core/database/table_models/__init__.py
phantom_core/database/table_models/ohlcv.py
phantom_core/database/utils/__init__.py
phantom_core/database/utils/connection.py
phantom_core/database/utils/get_ohlcv.py
phantom_core/database/utils/inspection.py
phantom_core/dataframe_transforms.py
phantom_core/datasource.py
phantom_core/db_utils.py
phantom_core/dvc.py
phantom_core/fname_parsing.py
phantom_core/logging.py
phantom_core/market_calendar.py
phantom_core/market_dataframe.py
phantom_core/mp.py
phantom_core/nb_setup.py
phantom_core/ohlcv.py
phantom_core/plotting/__init__.py
phantom_core/plotting/annotations.py
phantom_core/plotting/bar.py
phantom_core/plotting/sizing.py
phantom_core/plotting/time_series/__init__.py
phantom_core/plotting/time_series/basic.py
phantom_core/plotting/typing.py
phantom_core/polygon.py
phantom_core/pydantic.py
phantom_core/s3_utils.py
phantom_core/slack.py
phantom_core/state.py
phantom_core/testing/__init__.py
phantom_core/testing/ohlcv_aggs.py
phantom_core/tqdm.py
phantom_core/utils.py
phantom_core-0.0.18.dist-info/LICENSE
phantom_core-0.0.18.dist-info/METADATA
phantom_core-0.0.18.dist-info/WHEEL
phantom_core-0.0.18.dist-info/entry_points.txt
phantom_core-0.0.18.dist-info/RECORD
